LICENSE
README.md
setup.py
precise_lite/__init__.py
precise_lite/functions.py
precise_lite/model.py
precise_lite/network_runner.py
precise_lite/params.py
precise_lite/stats.py
precise_lite/threshold_decoder.py
precise_lite/train_data.py
precise_lite/util.py
precise_lite/vectorization.py
precise_lite.egg-info/PKG-INFO
precise_lite.egg-info/SOURCES.txt
precise_lite.egg-info/dependency_links.txt
precise_lite.egg-info/entry_points.txt
precise_lite.egg-info/requires.txt
precise_lite.egg-info/top_level.txt
precise_lite/scripts/add_noise.py
precise_lite/scripts/base_script.py
precise_lite/scripts/calc_threshold.py
precise_lite/scripts/collect.py
precise_lite/scripts/convert.py
precise_lite/scripts/engine.py
precise_lite/scripts/eval.py
precise_lite/scripts/graph.py
precise_lite/scripts/listen.py
precise_lite/scripts/simulate.py
precise_lite/scripts/test.py
precise_lite/scripts/train.py
precise_lite/scripts/train_generated.py
precise_lite/scripts/train_incremental.py
precise_lite/scripts/train_optimize.py
precise_lite/scripts/train_sampled.py