Metadata-Version: 2.1
Name: precise-lite
Version: 0.4.0a1
Summary: Mycroft Precise Wake Word Listener, Lite version (OpenVoiceOS)
Home-page: https://github.com/OpenVoiceOS/precise-lite
Author: Matthew Scholefield
Author-email: matthew.scholefield@mycroft.ai
License: Apache-2.0
Keywords: wakeword keyword wake word listener sound
Platform: UNKNOWN
Classifier: Development Status :: 3 - Alpha
Classifier: Intended Audience :: Developers
Classifier: Topic :: Text Processing :: Linguistic
Classifier: License :: OSI Approved :: Apache Software License
Classifier: Programming Language :: Python :: 3
Classifier: Programming Language :: Python :: 3.0
Classifier: Programming Language :: Python :: 3.1
Classifier: Programming Language :: Python :: 3.2
Classifier: Programming Language :: Python :: 3.3
Classifier: Programming Language :: Python :: 3.4
Classifier: Programming Language :: Python :: 3.5
Classifier: Programming Language :: Python :: 3.6
License-File: LICENSE
